#ifndef INSTRUCTIONS_H
#define INSTRUCTIONS_H

#define JVM_OPCODES(X) \
    X(nop, 0x00) \
    X(aconst_null, 0x01) \
    X(iconst_m1, 0x02) \
    X(iconst_0, 0x03) \
    X(iconst_1, 0x04) \
    X(iconst_2, 0x05) \
    X(iconst_3, 0x06) \
    X(iconst_4, 0x07) \
    X(iconst_5, 0x08) \
    X(lconst_0, 0x09) \
    X(lconst_1, 0x0a) \
    X(fconst_0, 0x0b) \
    X(fconst_1, 0x0c) \
    X(fconst_2, 0x0d) \
    X(dconst_0, 0x0e) \
    X(dconst_1, 0x0f) \
    X(bipush, 0x10) \
    X(sipush, 0x11) \
    X(ldc, 0x12) \
    X(ldc_w, 0x13) \
    X(ldc2_w, 0x14) \
    X(iload, 0x15) \
    X(lload, 0x16) \
    X(fload, 0x17) \
    X(dload, 0x18) \
    X(aload, 0x19) \
    X(iload_0, 0x1a) \
    X(iload_1, 0x1b) \
    X(iload_2, 0x1c) \
    X(iload_3, 0x1d) \
    X(lload_0, 0x1e) \
    X(lload_1, 0x1f) \
    X(lload_2, 0x20) \
    X(lload_3, 0x21) \
    X(fload_0, 0x22) \
    X(fload_1, 0x23) \
    X(fload_2, 0x24) \
    X(fload_3, 0x25) \
    X(dload_0, 0x26) \
    X(dload_1, 0x27) \
    X(dload_2, 0x28) \
    X(dload_3, 0x29) \
    X(aload_0, 0x2a) \
    X(aload_1, 0x2b) \
    X(aload_2, 0x2c) \
    X(aload_3, 0x2d) \
    X(iaload, 0x2e) \
    X(laload, 0x2f) \
    X(faload, 0x30) \
    X(daload, 0x31) \
    X(aaload, 0x32) \
    X(baload, 0x33) \
    X(caload, 0x34) \
    X(saload, 0x35) \
    X(istore, 0x36) \
    X(lstore, 0x37) \
    X(fstore, 0x38) \
    X(dstore, 0x39) \
    X(astore, 0x3a) \
    X(istore_0, 0x3b) \
    X(istore_1, 0x3c) \
    X(istore_2, 0x3d) \
    X(istore_3, 0x3e) \
    X(lstore_0, 0x3f) \
    X(lstore_1, 0x40) \
    X(lstore_2, 0x41) \
    X(lstore_3, 0x42) \
    X(fstore_0, 0x43) \
    X(fstore_1, 0x44) \
    X(fstore_2, 0x45) \
    X(fstore_3, 0x46) \
    X(dstore_0, 0x47) \
    X(dstore_1, 0x48) \
    X(dstore_2, 0x49) \
    X(dstore_3, 0x4a) \
    X(astore_0, 0x4b) \
    X(astore_1, 0x4c) \
    X(astore_2, 0x4d) \
    X(astore_3, 0x4e) \
    X(iastore, 0x4f) \
    X(lastore, 0x50) \
    X(fastore, 0x51) \
    X(dastore, 0x52) \
    X(aastore, 0x53) \
    X(bastore, 0x54) \
    X(castore, 0x55) \
    X(sastore, 0x56) \
    X(pop, 0x57) \
    X(pop2, 0x58) \
    X(dup, 0x59) \
    X(dup_x1, 0x5a) \
    X(dup_x2, 0x5b) \
    X(dup2, 0x5c) \
    X(dup2_x1, 0x5d) \
    X(dup2_x2, 0x5e) \
    X(swap, 0x5f) \
    X(iadd, 0x60) \
    X(ladd, 0x61) \
    X(fadd, 0x62) \
    X(dadd, 0x63) \
    X(isub, 0x64) \
    X(lsub, 0x65) \
    X(fsub, 0x66) \
    X(dsub, 0x67) \
    X(imul, 0x68) \
    X(lmul, 0x69) \
    X(fmul, 0x6a) \
    X(dmul, 0x6b) \
    X(idiv, 0x6c) \
    X(ldiv, 0x6d) \
    X(fdiv, 0x6e) \
    X(ddiv, 0x6f) \
    X(irem, 0x70) \
    X(lrem, 0x71) \
    X(frem, 0x72) \
    X(drem, 0x73) \
    X(ineg, 0x74) \
    X(lneg, 0x75) \
    X(fneg, 0x76) \
    X(dneg, 0x77) \
    X(ishl, 0x78) \
    X(lshl, 0x79) \
    X(ishr, 0x7a) \
    X(lshr, 0x7b) \
    X(iushr, 0x7c) \
    X(lushr, 0x7d) \
    X(iand, 0x7e) \
    X(land, 0x7f) \
    X(ior, 0x80) \
    X(lor, 0x81) \
    X(ixor, 0x82) \
    X(lxor, 0x83) \
    X(iinc, 0x84) \
    X(i2l, 0x85) \
    X(i2f, 0x86) \
    X(i2d, 0x87) \
    X(l2i, 0x88) \
    X(l2f, 0x89) \
    X(l2d, 0x8a) \
    X(f2i, 0x8b) \
    X(f2l, 0x8c) \
    X(f2d, 0x8d) \
    X(d2i, 0x8e) \
    X(d2l, 0x8f) \
    X(d2f, 0x90) \
    X(i2b, 0x91) \
    X(i2c, 0x92) \
    X(i2s, 0x93) \
    X(lcmp, 0x94) \
    X(fcmpl, 0x95) \
    X(fcmpg, 0x96) \
    X(dcmpl, 0x97) \
    X(dcmpg, 0x98) \
    X(ifeq, 0x99) \
    X(ifne, 0x9a) \
    X(iflt, 0x9b) \
    X(ifge, 0x9c) \
    X(ifgt, 0x9d) \
    X(ifle, 0x9e) \
    X(if_icmpeq, 0x9f) \
    X(if_icmpne, 0xa0) \
    X(if_icmplt, 0xa1) \
    X(if_icmpge, 0xa2) \
    X(if_icmpgt, 0xa3) \
    X(if_icmple, 0xa4) \
    X(if_acmpeq, 0xa5) \
    X(if_acmpne, 0xa6) \
    X(goto_, 0xa7) \
    X(jsr, 0xa8) \
    X(ret, 0xa9) \
    X(tableswitch, 0xaa) \
    X(lookupswitch, 0xab) \
    X(ireturn, 0xac) \
    X(lreturn, 0xad) \
    X(freturn, 0xae) \
    X(dreturn, 0xaf) \
    X(areturn, 0xb0) \
    X(return_, 0xb1) \
    X(getstatic, 0xb2) \
    X(putstatic, 0xb3) \
    X(getfield, 0xb4) \
    X(putfield, 0xb5) \
    X(invokevirtual, 0xb6) \
    X(invokespecial, 0xb7) \
    X(invokestatic, 0xb8) \
    X(invokeinterface, 0xb9) \
    X(invokedynamic, 0xba) \
    X(new_, 0xbb) \
    X(newarray, 0xbc) \
    X(anewarray, 0xbd) \
    X(arraylength, 0xbe) \
    X(athrow, 0xbf) \
    X(checkcast, 0xc0) \
    X(instanceof, 0xc1) \
    X(monitorenter, 0xc2) \
    X(monitorexit, 0xc3) \
    X(wide, 0xc4) \
    X(multianewarray, 0xc5) \
    X(ifnull, 0xc6) \
    X(ifnonnull, 0xc7) \
    X(goto_w, 0xc8) \
    X(jsr_w, 0xc9)

#endif